ttshandler/__init__.py
ttshandler/ttsexceptions.py
ttshandler/ttshandler.py
ttshandler-1.0.1.dist-info/METADATA
ttshandler-1.0.1.dist-info/WHEEL
ttshandler-1.0.1.dist-info/licenses/LICENSE
ttshandler-1.0.1.dist-info/RECORD
