Metadata-Version: 2.3
Name: ttshandler
Version: 1.0.1
Summary: A Python library that provides a simple and intuitive API for seamless interfacing with text-to-speech libraries like gtts and pyttsx3.
Project-URL: Homepage, https://github.com/ArijitKD/ttshandler
Project-URL: Repository, https://github.com/ArijitKD/ttshandler.git
Project-URL: Issues, https://github.com/ArijitKD/ttshandler/issues
Author-email: Arijit Kumar Das <arijitkdgit.official@gmail.com>
License-File: LICENSE
Keywords: Google Text to Speech,TTSHandler,Text to Speech,gtts,pyttsx3,tts
Classifier: Development Status :: 5 - Production/Stable
Classifier: Intended Audience :: Developers
Classifier: License :: OSI Approved :: MIT License
Classifier: Programming Language :: Python :: 3
Classifier: Programming Language :: Python :: 3.8
Classifier: Programming Language :: Python :: 3.9
Classifier: Programming Language :: Python :: 3.10
Classifier: Programming Language :: Python :: 3.11
Classifier: Programming Language :: Python :: 3.12
Classifier: Topic :: Software Development :: Build Tools
Requires-Python: >=3.8
Requires-Dist: gtts
Requires-Dist: matplotlib
Requires-Dist: numpy
Requires-Dist: pydub
Requires-Dist: pyttsx3
